pdkmaster/io/tasyag/__init__.py
pdkmaster/io/tasyag/doit.py
pdkmaster_io_tasyag-0.1.0.dist-info/METADATA
pdkmaster_io_tasyag-0.1.0.dist-info/WHEEL
pdkmaster_io_tasyag-0.1.0.dist-info/entry_points.txt
pdkmaster_io_tasyag-0.1.0.dist-info/licenses/LICENSE.md
pdkmaster_io_tasyag-0.1.0.dist-info/RECORD
