Metadata-Version: 2.1
Name: pdkmaster-io-tasyag
Version: 0.1.0
Summary: PDKMaster integration with HiTas/Yagle
Author: Project Arrakeen contributors
License: AGPL-3.0-or-later OR GPL-2.0-or-later OR CERN-OHL-S-2.0+ OR Apache-2.0
Requires-Python: >=3.8
Requires-Dist: PDKMaster~=0.12.0
